llamarch/__init__.py
llamarch/auth/__init__.py
llamarch/auth/authenticator.py
llamarch/common/__init__.py
llamarch/common/base_agent.py
llamarch/common/cache.py
llamarch/common/fine_tuner.py
llamarch/common/graph_db.py
llamarch/common/llm.py
llamarch/common/llm_embedding.py
llamarch/common/vector_db.py
llamarch/patterns/__init__.py
llamarch/patterns/agent_swarm/__init__.py
llamarch/patterns/agent_swarm/consensus.py
llamarch/patterns/agent_swarm/example.py
llamarch/patterns/knowledge_graph/__init__.py
llamarch/patterns/knowledge_graph/example.py
llamarch/patterns/layered_caching/__init__.py
llamarch/patterns/layered_caching/example.py
llamarch/patterns/memory_cognition/__init__.py
llamarch/patterns/memory_cognition/example.py
llamarch/patterns/memory_cognition/long_term_memory.py
llamarch/patterns/memory_cognition/memory_decay.py
llamarch/patterns/memory_cognition/short_term_memory.py
llamarch/patterns/memory_cognition/summarizer.py
llamarch/patterns/multiagent_feedback/__init__.py
llamarch/patterns/multiagent_feedback/agent_selector.py
llamarch/patterns/multiagent_feedback/example.py
llamarch/patterns/multiagent_feedback/feedback.py
llamarch/patterns/multiagent_feedback/output_integrator.py
llamarch/patterns/student_teacher/__init__.py
llamarch/patterns/student_teacher/example.py
llamarch/patterns/student_teacher/student.py
llamarch/patterns/student_teacher/teacher.py
LLaMArch-0.0.1.dist-info/LICENSE.md
LLaMArch-0.0.1.dist-info/METADATA
LLaMArch-0.0.1.dist-info/WHEEL
LLaMArch-0.0.1.dist-info/top_level.txt
LLaMArch-0.0.1.dist-info/RECORD
