Metadata-Version: 2.1
Name: LLaMArch
Version: 0.0.1
Summary: Building Block Architectures for GenAI
Home-page: https://github.com/gpavanb1/llamarch-docs
Author: gpavanb1
Author-email: gpavanb@gmail.com
License: CC BY-NC 4.0 for non-commercial use, commercial license available
Project-URL: Bug Reports, https://github.com/gpavanb1/llamarch-docs/issues
Project-URL: Source, https://github.com/gpavanb1/llamarch-docs/
Keywords: genai architecture ai patterns machine-learning llm langchain
Classifier: Topic :: Scientific/Engineering :: Artificial Intelligence
Classifier: License :: Other/Proprietary License
Classifier: Programming Language :: Python :: 3
Classifier: Programming Language :: Python :: 3 :: Only
License-File: LICENSE.md
Requires-Dist: langchain
